Metadata-Version: 2.1
Name: Testing-sample2
Version: 0.2.0
Summary: This PIP package used for testing
Author: zebu
Author-email: venkateshnsm@gmail.com
Classifier: Programming Language :: Python :: 3
Classifier: Operating System :: OS Independent
Requires-Python: >=3.6
